nonebot_plugin_access_control/__init__.py
nonebot_plugin_access_control/alc.py
nonebot_plugin_access_control/config.py
nonebot_plugin_access_control/handler/__init__.py
nonebot_plugin_access_control/handler/help_handler.py
nonebot_plugin_access_control/handler/limit_handler.py
nonebot_plugin_access_control/handler/permission_handler.py
nonebot_plugin_access_control/handler/service_handler.py
nonebot_plugin_access_control/handler/subject_handler.py
nonebot_plugin_access_control/handler/utils/__init__.py
nonebot_plugin_access_control/handler/utils/env.py
nonebot_plugin_access_control/handler/utils/errors.py
nonebot_plugin_access_control/handler/utils/permission.py
nonebot_plugin_access_control/matcher.py
nonebot_plugin_access_control/orm_migrations/96ced46e72e9_data_migrate.py
nonebot_plugin_access_control/orm_migrations/9bb3231cf9aa_init_db.py
nonebot_plugin_access_control/repository/__init__.py
nonebot_plugin_access_control/repository/orm/__init__.py
nonebot_plugin_access_control/repository/orm/permission.py
nonebot_plugin_access_control/repository/orm/rate_limit.py
nonebot_plugin_access_control/repository/permission/__init__.py
nonebot_plugin_access_control/repository/permission/impl.py
nonebot_plugin_access_control/repository/permission/interface.py
nonebot_plugin_access_control/repository/rate_limit/__init__.py
nonebot_plugin_access_control/repository/rate_limit/impl.py
nonebot_plugin_access_control/repository/rate_limit/interface.py
nonebot_plugin_access_control/repository/rate_limit_token/__init__.py
nonebot_plugin_access_control/repository/rate_limit_token/datastore.py
nonebot_plugin_access_control/repository/rate_limit_token/inmemory.py
nonebot_plugin_access_control/repository/rate_limit_token/interface.py
nonebot_plugin_access_control/repository/utils.py
nonebot_plugin_access_control/script/__init__.py
nonebot_plugin_access_control/service/__init__.py
nonebot_plugin_access_control/service/_impl/__init__.py
nonebot_plugin_access_control-1.2.4.dist-info/LICENSE
nonebot_plugin_access_control-1.2.4.dist-info/METADATA
nonebot_plugin_access_control-1.2.4.dist-info/WHEEL
nonebot_plugin_access_control-1.2.4.dist-info/entry_points.txt
nonebot_plugin_access_control-1.2.4.dist-info/RECORD
