Metadata-Version: 2.3
Name: nonebot-plugin-access-control
Version: 1.2.4
Summary: 
License: MIT
Author: ssttkkl
Author-email: huang.wen.long@hotmail.com
Requires-Python: >=3.9,<4.0
Classifier: License :: OSI Approved :: MIT License
Classifier: Programming Language :: Python :: 3
Classifier: Programming Language :: Python :: 3.9
Classifier: Programming Language :: Python :: 3.10
Classifier: Programming Language :: Python :: 3.11
Classifier: Programming Language :: Python :: 3.12
Classifier: Programming Language :: Python :: 3.13
Provides-Extra: cli
Provides-Extra: migrate
Requires-Dist: arclet-alconna (>=1.7.24,<2.0.0)
Requires-Dist: nonebot-plugin-access-control-api (>=1.2.1,<2.0.0)
Requires-Dist: nonebot-plugin-apscheduler (>=0.3.0)
Requires-Dist: nonebot-plugin-orm (>=0.7.0,<1.0.0)
Requires-Dist: nonebot-plugin-session (>=0.3.0,<0.4.0)
Requires-Dist: nonebot2 (>=2.3.0,<3.0.0)
Requires-Dist: pytimeparser (>=0.2.0,<0.3.0)
Requires-Dist: shortuuid (>=1.0.11,<2.0.0)
Project-URL: Repository, https://github.com/bot-ssttkkl/nonebot-plugin-access-control
